SnakeCode/__init__.py
SnakeCode/digikala.py
SnakeCode/rubino.py
snakecode-1.0.0.dist-info/METADATA
snakecode-1.0.0.dist-info/WHEEL
snakecode-1.0.0.dist-info/top_level.txt
snakecode-1.0.0.dist-info/RECORD
